XTBApi/__init__.py
XTBApi/__version__.py
XTBApi/api.py
XTBApi/exceptions.py
monedadigitalx-1.0a7.post2.dist-info/METADATA
monedadigitalx-1.0a7.post2.dist-info/WHEEL
monedadigitalx-1.0a7.post2.dist-info/top_level.txt
monedadigitalx-1.0a7.post2.dist-info/RECORD
