Metadata-Version: 2.1
Name: monedadigitalx
Version: 1.0a7.post2
Summary: A python based API for XTB trading using websocket_client.
Home-page: https://github.com/AmadoRamos/XTBApi.git
Download-URL: https://github.com/AmadoRamos/XTBApi/archive/refs/tags/v1.0a7r2.zip
Author: federico123579
Author-email: federico123579@gmail.com
License: MIT License
Classifier: Programming Language :: Python :: 3.6
Requires-Python: >=3.6.0
Requires-Dist: requests
Requires-Dist: websocket-client
